{
    "link 0": "https://twitter.com/thehackersnews",
    "link 1": "https://www.linkedin.com/company/thehackernews/",
    "link 2": "https://www.facebook.com/thehackernews",
    "link 3": "https://thehackernews.com/",
    "link 4": "https://thehackernews.com#email-outer",
    "link 5": "https://thehackernews.com/",
    "link 6": "https://thehackernews.com#email-outer",
    "link 7": "https://thehackernews.com/p/upcoming-hacker-news-webinars.html",
    "link 8": "https://thehackernews.com/",
    "link 9": "https://thehackernews.com/search/label/data%20breach",
    "link 10": "https://thehackernews.com/search/label/Cyber%20Attack",
    "link 11": "https://thehackernews.com/search/label/Vulnerability",
    "link 12": "https://thehackernews.com/p/upcoming-hacker-news-webinars.html",
    "link 13": "https://thehackernews.com/expert-insights/",
    "link 14": "https://thehackernews.com/p/submit-news.html",
    "link 15": "https://thehackernews.com/p/upcoming-hacker-news-webinars.html",
    "link 16": "https://thehackernews.tradepub.com",
    "link 17": "https://thehackernews.com/p/about-us.html",
    "link 18": "https://thehackernews.com/p/careers-technical-writer-designer-and.html",
    "link 19": "https://thehackernews.com/p/advertising-with-hacker-news.html",
    "link 20": "https://thehackernews.com/p/submit-news.html",
    "link 21": "https://www.facebook.com/thehackernews",
    "link 22": "https://twitter.com/thehackersnews",
    "link 23": "https://www.linkedin.com/company/thehackernews/",
    "link 24": "https://www.youtube.com/c/thehackernews?sub_confirmation=1",
    "link 25": "https://www.instagram.com/thehackernews/",
    "link 26": "https://feeds.feedburner.com/TheHackersNews",
    "link 27": "https://thehackernews.com#email-outer",
    "link 28": "https://thehackernews.com/2025/09/lastpass-warns-of-fake-repositories.html?m=1",
    "link 29": "https://thehackernews.com/2025/07/weekly-recap-sharepoint-0-day-chrome.html?m=1",
    "link 30": "https://thehackernews.com/2025/07/weekly-recap-scattered-spider-arrests.html?m=1",
    "link 31": "https://thehackernews.uk/leadership-hub-2",
    "link 32": "https://thehackernews.uk/zscaler-threat-insights",
    "link 33": "https://thehackernews.com/2025/07/tag-140-deploys-drat-v2-rat-targeting.html?m=1",
    "link 34": "https://thehackernews.com/2025/02/thn-weekly-recap-top-cybersecurity.html?m=1",
    "link 35": "https://thehackernews.com/2025/01/thn-weekly-recap-top-cybersecurity_27.html?m=1",
    "link 36": "https://thehackernews.com/2025/01/thn-weekly-recap-top-cybersecurity_20.html?m=1",
    "link 37": "https://thehackernews.com/2025/01/thn-weekly-recap-top-cybersecurity_01424177917.html?m=1",
    "link 38": "https://thehackernews.com/search/label/hacking%20news?updated-max=2025-01-13T17:35:00%2B05:30&max-results=20&start=8&by-date=false&m=1",
    "link 39": "https://thehackernews.com/expert-insights/",
    "link 40": "https://thehackernews.com/videos/",
    "link 41": "https://thehackernews.com/expert-insights/2025/09/taming-ais-threat-vectors-why-cisos.html",
    "link 42": "https://thehackernews.com/expert-insights/2025/09/the-limitations-of-vpn-based-access-for.html",
    "link 43": "https://thehackernews.com/expert-insights/2025/09/soc-for-all-why-every-company-can-now.html",
    "link 44": "https://thehackernews.com/expert-insights/2025/09/how-to-build-identity-firewall-with.html",
    "link 45": "https://thehackernews.uk/k8s-error-playbook",
    "link 46": "https://thehackernews.uk/gitguard-interactive",
    "link 47": "https://thehackernews.uk/siem-third-act",
    "link 48": "https://thehackernews.uk/ctem-5-stages-guide-native",
    "link 49": "https://twitter.com/thehackersnews",
    "link 50": "https://www.linkedin.com/company/thehackernews/",
    "link 51": "https://www.youtube.com/c/thehackernews?sub_confirmation=1",
    "link 52": "https://www.instagram.com/thehackernews/",
    "link 53": "https://www.facebook.com/thehackernews",
    "link 54": "https://news.google.com/publications/CAAqLQgKIidDQklTRndnTWFoTUtFWFJvWldoaFkydGxjbTVsZDNNdVkyOXRLQUFQAQ",
    "link 55": "https://thehackernews.com/p/about-us.html",
    "link 56": "https://thehackernews.com/p/advertising-with-hacker-news.html",
    "link 57": "https://thehackernews.com/p/submit-news.html",
    "link 58": "https://thehackernews.com/p/upcoming-hacker-news-webinars.html",
    "link 59": "https://thehackernews.com/p/privacy-policy.html",
    "link 60": "https://feeds.feedburner.com/TheHackersNews",
    "link 61": "https://thehackernews.com/p/submit-news.html"
}